pydeskui/__init__.py
pydeskui/button.py
pydeskui/demo.py
pydeskui/input.py
pydeskui/list.py
pydeskui/assets/img/download.svg
pydeskui/assets/img/download_test.svg
pydeskui/assets/img/logo.ico
pydeskui/assets/img/logo.png
pydeskui/common/__init__.py
pydeskui/common/const.py
pydeskui/common/svg_image.py
pydeskui/common/util.py
pydeskui/tk/basic-widgets.py
pydeskui/tk/cursor.py
pydeskui/tk/event-loop.py
pydeskui/tk/grid.py
pydeskui/tk/listbox.py
pydeskui/tk/more-widgets.py
pydeskui/tk/tk.py
pydeskui/tk/validation.py
pydeskui-0.0.1.dist-info/LICENSE
pydeskui-0.0.1.dist-info/METADATA
pydeskui-0.0.1.dist-info/WHEEL
pydeskui-0.0.1.dist-info/top_level.txt
pydeskui-0.0.1.dist-info/RECORD
