Metadata-Version: 2.1
Name: pydeskui
Version: 0.0.1
Summary: Python TKinter Simple UI Components
Home-page: https://github.com/openHacking/TKinter-UI
Author: openHacking
Author-email: openHacking <openHacking@126.com>
License: The MIT License (MIT)        
Project-URL: Homepage, https://github.com/openHacking/TKinter-UI
Project-URL: Bug Tracker, https://github.com/openHacking/TKinter-UI/issues
Keywords: python,GUI,tkinter,UI
Classifier: Development Status :: 3 - Alpha
Classifier: Intended Audience :: Developers
Classifier: Topic :: Software Development :: Build Tools
Classifier: Programming Language :: Python :: 3
Classifier: License :: OSI Approved :: MIT License
Classifier: Operating System :: OS Independent
Requires-Python: >=3.7
License-File: LICENSE
Requires-Dist: lxml (==4.7.1)
Requires-Dist: Pillow (==9.0.1)
Requires-Dist: tksvg (==0.7.4)
